pygadm/__init__.py
pygadm/bin/refresh_database.py
pygadm/data/gadm_continent.json
pygadm/data/gadm_database.parquet
pygadm-0.5.3.dist-info/METADATA
pygadm-0.5.3.dist-info/WHEEL
pygadm-0.5.3.dist-info/licenses/AUTHORS.rst
pygadm-0.5.3.dist-info/licenses/LICENSE
pygadm-0.5.3.dist-info/RECORD
