Metadata-Version: 2.3
Name: pygadm
Version: 0.5.3
Summary: Easy access to administrative boundary defined by GADM from Python scripts
Project-URL: Homepage, https://github.com/12rambau/pygadm
Author-email: Pierrick Rambaud <pierrick.rambaud49@gmail.com>
License: MIT
License-File: AUTHORS.rst
License-File: LICENSE
Keywords: Python
Classifier: Development Status :: 3 - Alpha
Classifier: Intended Audience :: Developers
Classifier: License :: OSI Approved :: MIT License
Classifier: Programming Language :: Python :: 3.8
Classifier: Programming Language :: Python :: 3.9
Classifier: Programming Language :: Python :: 3.10
Classifier: Programming Language :: Python :: 3.11
Requires-Python: >=3.8
Requires-Dist: deprecated>=1.2.14
Requires-Dist: geopandas
Requires-Dist: pyarrow
Requires-Dist: requests-cache
Provides-Extra: doc
Requires-Dist: geemap; extra == 'doc'
Requires-Dist: httplib2; extra == 'doc'
Requires-Dist: ipykernel; extra == 'doc'
Requires-Dist: ipyleaflet; extra == 'doc'
Requires-Dist: jupyter-sphinx; extra == 'doc'
Requires-Dist: pydata-sphinx-theme; extra == 'doc'
Requires-Dist: sphinx-autoapi; extra == 'doc'
Requires-Dist: sphinx-copybutton; extra == 'doc'
Requires-Dist: sphinx-design; extra == 'doc'
Requires-Dist: sphinx-favicon; extra == 'doc'
Requires-Dist: sphinx<7; extra == 'doc'
Provides-Extra: test
Requires-Dist: pytest; extra == 'test'
Requires-Dist: pytest-cov; extra == 'test'
Requires-Dist: pytest-deadfixtures; extra == 'test'
Requires-Dist: pytest-regressions>=2.4.3; extra == 'test'
Requires-Dist: pytest-sugar; extra == 'test'
